{
    "csv_ex22_3.csv": {
        "size": 320,
        "last recent mtime": 1602089344.9331837,
        "last recent human read": "2020-10-07 20:49:04"
    },
    "csv_from_dict_ex22_2.csv": {
        "size": 183,
        "last recent mtime": 1602006344.232435,
        "last recent human read": "2020-10-06 21:45:44"
    },
    "EX18.py": {
        "size": 1873,
        "last recent mtime": 1600714640.6997845,
        "last recent human read": "2020-09-21 22:57:20"
    },
    "EX19.py": {
        "size": 2007,
        "last recent mtime": 1601197658.7709415,
        "last recent human read": "2020-09-27 13:07:38"
    },
    "EX20.py": {
        "size": 2721,
        "last recent mtime": 1601405994.0857751,
        "last recent human read": "2020-09-29 22:59:54"
    },
    "EX21.py": {
        "size": 2182,
        "last recent mtime": 1601838317.5795336,
        "last recent human read": "2020-10-04 23:05:17"
    },
    "EX22.py": {
        "size": 2359,
        "last recent mtime": 1602091854.8644242,
        "last recent human read": "2020-10-07 21:30:54"
    },
    "EX23.py": {
        "size": 4824,
        "last recent mtime": 1602095852.6509976,
        "last recent human read": "2020-10-07 22:37:32"
    },
    "example_csv.py": {
        "size": 150,
        "last recent mtime": 1602002921.528111,
        "last recent human read": "2020-10-06 20:48:41"
    },
    "examp_csv_text.txt": {
        "size": 24,
        "last recent mtime": 1602004751.646183,
        "last recent human read": "2020-10-06 21:19:11"
    },
    "files_data_in_dir.json": {
        "size": 3554,
        "last recent mtime": 1602095813.4817526,
        "last recent human read": "2020-10-07 22:36:53"
    },
    "for_18_2.txt": {
        "size": 36,
        "last recent mtime": 1600710427.852151,
        "last recent human read": "2020-09-21 21:47:07"
    },
    "mini-access-log.txt": {
        "size": 36562,
        "last recent mtime": 1602095787.807522,
        "last recent human read": "2020-10-07 22:36:27"
    },
    "output.csv": {
        "size": 527,
        "last recent mtime": 1602005117.9056535,
        "last recent human read": "2020-10-06 21:25:17"
    },
    "output_ex22_1_ex23_1.csv": {
        "size": 2602,
        "last recent mtime": 1602091754.6798918,
        "last recent human read": "2020-10-07 21:29:14"
    },
    "output_ex23_1.json": {
        "size": 6373,
        "last recent mtime": 1602090863.6135156,
        "last recent human read": "2020-10-07 21:14:23"
    },
    "output_ex23_2.json": {
        "size": 8860,
        "last recent mtime": 1602093093.784608,
        "last recent human read": "2020-10-07 21:51:33"
    },
    "passwd": {
        "size": 2644,
        "last recent mtime": 1602003379.1968637,
        "last recent human read": "2020-10-06 20:56:19"
    },
    "stix.txt": {
        "size": 2058,
        "last recent mtime": 1601403339.6944833,
        "last recent human read": "2020-09-29 22:15:39"
    },
    "stix_for_18_3.txt": {
        "size": 378,
        "last recent mtime": 1600712760.064986,
        "last recent human read": "2020-09-21 22:26:00"
    },
    "use_hashlib.py": {
        "size": 1907,
        "last recent mtime": 1601492681.6504323,
        "last recent human read": "2020-09-30 23:04:41"
    },
    "wcfile.txt": {
        "size": 174,
        "last recent mtime": 1601401487.538956,
        "last recent human read": "2020-09-29 21:44:47"
    }
}